setup.cfg
setup.py
chevrons/__init__.py
chevrons/pipeline_base.py
chevrons/pipeline_extra.py
chevrons/pipeline_hof.py
chevrons/pipeline_parallel.py
chevrons.egg-info/PKG-INFO
chevrons.egg-info/SOURCES.txt
chevrons.egg-info/dependency_links.txt
chevrons.egg-info/top_level.txt
chevrons/tests/__init__.py
chevrons/tests/examples.py
chevrons/tests/performance_tests.py
chevrons/tests/tests.py