Metadata-Version: 1.1
Name: chevrons
Version: 0.1.3
Summary: Rapidly build pipelines for out-of-core data processing using higher order functions.
Home-page: https://github.com/lmc2179/chevrons
Author: Louis Cialdella
Author-email: louiscialdella@gmail.com
License: UNKNOWN
Keywords: parallel,functional,map,reduce,fold,pipeline,stream
Platform: UNKNOWN
Classifier: Programming Language :: Python :: 3 :: Only
